pycounts_dw/__init__.py
pycounts_dw/plotting.py
pycounts_dw/pycounts_dw.py
pycounts_dw-0.1.0.dist-info/LICENSE
pycounts_dw-0.1.0.dist-info/METADATA
pycounts_dw-0.1.0.dist-info/WHEEL
pycounts_dw-0.1.0.dist-info/RECORD
